safe_exec/__init__.py
safe_exec/py.typed
safe_exec-0.0.2.dist-info/LICENSE.txt
safe_exec-0.0.2.dist-info/METADATA
safe_exec-0.0.2.dist-info/WHEEL
safe_exec-0.0.2.dist-info/top_level.txt
safe_exec-0.0.2.dist-info/RECORD
