Metadata-Version: 2.2
Name: safe-exec
Version: 0.0.2
Summary: Deobfuscate and inspect code passed into exec() and eval()
Author-email: Lemonyte <contact@lemonyte.com>
License: MIT License
Project-URL: Repository, https://github.com/lemonyte/safe-exec
Requires-Python: >=3.9
License-File: LICENSE.txt
Requires-Dist: typing-extensions>=4.0.0; python_version < "3.10"
